ketza/__init__.py
ketza/_elements.py
ketza/format.py
ketza/tags.py
ketza-2.0.1.dist-info/METADATA
ketza-2.0.1.dist-info/WHEEL
ketza-2.0.1.dist-info/top_level.txt
ketza-2.0.1.dist-info/RECORD
