Metadata-Version: 2.1
Name: ketza
Version: 2.0.1
Summary: A python engine for building html components
Author-email: Charlie Paterson <Charlieed.paterson@googlemail.com>
Project-URL: Homepage, https://github.com/CpaterCodes/Ketza
Keywords: html,ketza,web,full stack
Classifier: License :: OSI Approved :: MIT License
Classifier: Development Status :: 5 - Production/Stable
Classifier: Operating System :: OS Independent
Requires-Python: >=3.6
Provides-Extra: dev
Requires-Dist: pipenv ; extra == 'dev'
Requires-Dist: pytest ; extra == 'dev'
